Metadata-Version: 2.4
Name: auto_codex
Version: 0.1.0
Summary: Advanced automation framework for Codex AI with comprehensive health monitoring, multi-provider support, and powerful log parsing capabilities
Home-page: https://github.com/Joseph Schlesinger/auto_codex
Author: Joseph Schlesinger
Author-email: Joseph Schlesinger <joe@schlesinger.io>
Maintainer-email: Joseph Schlesinger <joe@schlesinger.io>
License: MIT
Project-URL: Homepage, https://github.com/Joseph Schlesinger/auto_codex
Project-URL: Repository, https://github.com/Joseph Schlesinger/auto_codex
Project-URL: Documentation, https://auto-codex.readthedocs.io/
Project-URL: Bug Tracker, https://github.com/Joseph Schlesinger/auto_codex/issues
Keywords: ai,codex,automation,health-monitoring,multi-provider,log-parsing
Classifier: Development Status :: 4 - Beta
Classifier: Intended Audience :: Developers
Classifier: Topic :: Software Development :: Libraries :: Python Modules
Classifier: Topic :: Scientific/Engineering :: Artificial Intelligence
Classifier: License :: OSI Approved :: MIT License
Classifier: Programming Language :: Python :: 3
Classifier: Programming Language :: Python :: 3.8
Classifier: Programming Language :: Python :: 3.9
Classifier: Programming Language :: Python :: 3.10
Classifier: Programming Language :: Python :: 3.11
Classifier: Programming Language :: Python :: 3.12
Requires-Python: >=3.8
License-File: LICENSE
Requires-Dist: pydantic>=2.0.0
Requires-Dist: jinja2>=3.0.0
Requires-Dist: pyyaml>=6.0.0
Requires-Dist: colorama>=0.4.6
Provides-Extra: dev
Requires-Dist: pytest>=7.0.0; extra == "dev"
Requires-Dist: pytest-cov>=4.0.0; extra == "dev"
Requires-Dist: pytest-asyncio>=0.21.0; extra == "dev"
Requires-Dist: black>=22.0.0; extra == "dev"
Requires-Dist: flake8>=5.0.0; extra == "dev"
Requires-Dist: mypy>=1.0.0; extra == "dev"
Requires-Dist: isort>=5.0.0; extra == "dev"
Provides-Extra: docs
Requires-Dist: sphinx>=5.0.0; extra == "docs"
Requires-Dist: sphinx-rtd-theme>=1.0.0; extra == "docs"
Requires-Dist: sphinx-autodoc-typehints>=1.12.0; extra == "docs"
Dynamic: author
Dynamic: home-page
Dynamic: license-file
Dynamic: requires-python
